json_anatomy-0.2.0.dist-info/licenses/LICENSE
json_anatomy-0.2.0.dist-info/licenses/NOTICE
jsonanatomy/Explore.py
jsonanatomy/Maybe.py
jsonanatomy/SimpleXML.py
jsonanatomy/Xplore.py
jsonanatomy/__init__.py
jsonanatomy/_version.py
jsonanatomy/file_reader.py
jsonanatomy/py.typed
json_anatomy-0.2.0.dist-info/METADATA
json_anatomy-0.2.0.dist-info/WHEEL
json_anatomy-0.2.0.dist-info/top_level.txt
json_anatomy-0.2.0.dist-info/RECORD
