Metadata-Version: 2.4
Name: json-anatomy
Version: 0.2.0
Summary: Scout, explore, infer, and analyze JSON structure and navigate data safely with intuitive exploration tools.
Author-email: Chathura Jayalath <acj.chathura@gmail.com>
Maintainer-email: Chathura Jayalath <acj.chathura@gmail.com>
License: Apache-2.0
Project-URL: Homepage, https://github.com/deamonpog/json-anatomy
Project-URL: Documentation, https://deamonpog.github.io/json-anatomy/
Project-URL: Repository, https://github.com/deamonpog/json-anatomy
Project-URL: Bug Tracker, https://github.com/deamonpog/json-anatomy/issues
Project-URL: Changelog, https://github.com/deamonpog/json-anatomy/releases
Keywords: json,schema,structure,introspection,navigation,analysis,exploration,data-science,api
Classifier: Development Status :: 4 - Beta
Classifier: Intended Audience :: Developers
Classifier: Intended Audience :: Information Technology
Classifier: Intended Audience :: Science/Research
Classifier: License :: OSI Approved :: Apache Software License
Classifier: Operating System :: OS Independent
Classifier: Programming Language :: Python :: 3
Classifier: Programming Language :: Python :: 3.7
Classifier: Programming Language :: Python :: 3.8
Classifier: Programming Language :: Python :: 3.9
Classifier: Programming Language :: Python :: 3.10
Classifier: Programming Language :: Python :: 3.11
Classifier: Programming Language :: Python :: 3.12
Classifier: Topic :: Software Development :: Libraries :: Python Modules
Classifier: Topic :: Utilities
Classifier: Topic :: Text Processing
Classifier: Topic :: Scientific/Engineering :: Information Analysis
Classifier: Typing :: Typed
Requires-Python: >=3.7
License-File: LICENSE
License-File: NOTICE
Requires-Dist: lxml>=4.9.0
Provides-Extra: dev
Requires-Dist: pytest>=6.0; extra == "dev"
Requires-Dist: pytest-cov; extra == "dev"
Requires-Dist: black; extra == "dev"
Requires-Dist: flake8; extra == "dev"
Requires-Dist: mypy; extra == "dev"
Requires-Dist: isort; extra == "dev"
Provides-Extra: docs
Requires-Dist: mkdocs>=1.4.0; extra == "docs"
Requires-Dist: mkdocs-material>=8.0.0; extra == "docs"
Requires-Dist: mkdocstrings[python]>=0.18.0; extra == "docs"
Dynamic: license-file
